[
  {
    "index": 0,
    "category": "New In",
    "endpoint": "new-in/"
  },
  {
    "index": 1,
    "category": "Demo Category",
    "endpoint": "demo-category/"
  },
  {
    "index": 2,
    "category": "Clothes",
    "endpoint": "clothes/"
  },
  {
    "index": 3,
    "category": "Accessories",
    "endpoint": "accessories/"
  },
  {
    "index": 4,
    "category": "Jewellery",
    "endpoint": "jewellery/"
  },
  {
    "index": 5,
    "category": "Shoes",
    "endpoint": "shoes/"
  },
  {
    "index": 6,
    "category": "Sale",
    "endpoint": "sale/"
  }
]